rohe/__init__.py
rohe/variable.py
rohe/api/agent_manager_resource.py
rohe/api/orchestration_resource.py
rohe/api/registration_resource.py
rohe/common/__init__.py
rohe/common/data_models.py
rohe/common/logger.py
rohe/common/performance.py
rohe/common/rest_service.py
rohe/common/rohe_enum.py
rohe/common/rohe_utils.py
rohe/common/window.py
rohe/external/__init__.py
rohe/external/k8s/generate_k8s_datamodel.sh
rohe/external/k8s/datamodel/api/apps/__init__.py
rohe/external/k8s/datamodel/api/apps/v1.py
rohe/external/k8s/datamodel/api/authentication/__init__.py
rohe/external/k8s/datamodel/api/authentication/v1.py
rohe/external/k8s/datamodel/api/autoscaling/__init__.py
rohe/external/k8s/datamodel/api/autoscaling/v1.py
rohe/external/k8s/datamodel/api/policy/__init__.py
rohe/external/k8s/datamodel/api/policy/v1.py
rohe/external/k8s/datamodel/apimachinery/pkg/__init__.py
rohe/external/k8s/datamodel/apimachinery/pkg/runtime.py
rohe/external/k8s/datamodel/apimachinery/pkg/api/__init__.py
rohe/external/k8s/datamodel/apimachinery/pkg/api/resource.py
rohe/external/k8s/datamodel/apimachinery/pkg/apis/meta/__init__.py
rohe/external/k8s/datamodel/apimachinery/pkg/apis/meta/v1.py
rohe/external/k8s/datamodel/apimachinery/pkg/util/__init__.py
rohe/external/k8s/datamodel/apimachinery/pkg/util/intstr.py
rohe/external/yolo/__init__.py
rohe/external/yolo/class.yml
rohe/external/yolo/model_loader.py
rohe/external/yolo/prediction_processing.py
rohe/external/yolo/yolov5.py
rohe/external/yolo/yolov8.py
rohe/lib/__init__.py
rohe/lib/utils/mess_logging.py
rohe/lib/utils/step_run.py
rohe/lib/utils/deployment/dag.py
rohe/lib/utils/deployment/generate_deployment.py
rohe/lib/utils/deployment/k3s.py
rohe/lib/utils/deployment/profiling_deployment.py
rohe/lib/utils/deployment/readme.md
rohe/lib/utils/deployment/DAG/default/image_build/readme.md
rohe/lib/utils/deployment/DAG/default/image_build/core_function/task.py
rohe/lib/utils/deployment/DAG/default/image_build/core_function/task_handler.py
rohe-0.0.9.dist-info/METADATA
rohe-0.0.9.dist-info/WHEEL
rohe-0.0.9.dist-info/licenses/LICENSE.txt
rohe-0.0.9.dist-info/RECORD
