Metadata-Version: 2.3
Name: rohe
Version: 0.0.9
Summary: An orchestration framework for End-to-End Machine Learning Serving with Resource Optimization on Heterogeneous Edge
Author-email: AaltoSEA <tri.m.nguyen@aalto.fi>
Maintainer-email: AaltoSEA <tri.m.nguyen@aalto.fi>, nguu0123 <nguu0123@gmail.com>
License: Apache-2.0
License-File: LICENSE.txt
Classifier: Development Status :: 2 - Pre-Alpha
Classifier: License :: OSI Approved :: Apache Software License
Classifier: Programming Language :: Python :: 3.10
Requires-Dist: boto3>=1.34.147
Requires-Dist: flask-restful==0.3.10
Requires-Dist: flask==2.2.3
Requires-Dist: gunicorn>=22.0.0
Requires-Dist: jinja2==3.1.2
Requires-Dist: kubernetes==30.1.0
Requires-Dist: lazy-import>=0.2.2
Requires-Dist: numpy==1.23.5
Requires-Dist: paho-mqtt==1.6.1
Requires-Dist: pandas==1.4.3
Requires-Dist: pydantic<2.8,>=2.7.4
Requires-Dist: pymongo==4.3.3
Requires-Dist: pyyaml==6.0.1
Requires-Dist: qoa4ml>=0.2.14
Requires-Dist: setuptools>=70.3.0
Requires-Dist: werkzeug==2.2.2
Provides-Extra: docs
Requires-Dist: mkdocs-awesome-pages-plugin>=2.9.2; extra == 'docs'
Requires-Dist: mkdocs-click>=0.8.1; extra == 'docs'
Requires-Dist: mkdocs-material; extra == 'docs'
Provides-Extra: yolo
Requires-Dist: gitpython>=3.1.43; extra == 'yolo'
Requires-Dist: ultralytics>=8.2.58; extra == 'yolo'
